epubmangler/__init__.py
epubmangler/epub.py
epubmangler/functions.py
epubmangler/globals.py
epubmangler-0.1.0.dist-info/METADATA
epubmangler-0.1.0.dist-info/WHEEL
epubmangler-0.1.0.dist-info/licenses/LICENSE
epubmangler-0.1.0.dist-info/RECORD
