Metadata-Version: 2.3
Name: epubmangler
Version: 0.1.0
Summary: Tools to modify the metadata of .epub format ebooks
Project-URL: Homepage, https://github.com/davekeogh/epubmangler
Project-URL: Issues, https://github.com/davekeogh/epubmangler/issues
Author-email: David Keogh <davidtkeogh@gmail.com>
Keywords: book,epub
Classifier: Development Status :: 4 - Beta
Classifier: Intended Audience :: Developers
Classifier: License :: OSI Approved :: BSD License
Classifier: Operating System :: OS Independent
Classifier: Programming Language :: Python :: 3
Requires-Python: >=3.8
